k3awssign/__init__.py
k3awssign/awssign.py
k3awssign/synopsis.py
k3awssign-0.1.4.dist-info/licenses/LICENSE
k3awssign-0.1.4.dist-info/METADATA
k3awssign-0.1.4.dist-info/WHEEL
k3awssign-0.1.4.dist-info/top_level.txt
k3awssign-0.1.4.dist-info/RECORD
